django_telescope/__init__.py
django_telescope/server_fastmcp.py
django_telescope-0.1.3.dist-info/METADATA
django_telescope-0.1.3.dist-info/WHEEL
django_telescope-0.1.3.dist-info/entry_points.txt
django_telescope-0.1.3.dist-info/licenses/LICENSE
django_telescope-0.1.3.dist-info/RECORD
